fca_api-1.0.0.dist-info/METADATA
fca_api-1.0.0.dist-info/WHEEL
fca_api-1.0.0.dist-info/entry_points.txt
fca_api-1.0.0.dist-info/licenses/LICENSE
fca_api/__init__.py
fca_api/__version__.py
fca_api/async_api.py
fca_api/const.py
fca_api/exc.py
fca_api/raw_api.py
fca_api/raw_status_codes.py
fca_api/types/__init__.py
fca_api/types/base.py
fca_api/types/field_parsers.py
fca_api/types/firm.py
fca_api/types/individual.py
fca_api/types/markets.py
fca_api/types/pagination.py
fca_api/types/products.py
fca_api/types/search.py
fca_api/types/settings.py
fca_api-1.0.0.dist-info/RECORD
