Metadata-Version: 2.4
Name: fca-api
Version: 1.0.0
Summary: Python client library for the UK Financial Services (FCA) Register RESTful API
Keywords: financial conduct authority,FCA,financial data,financial regulation,financial services register,financial services,prudential regulation authority,regulated markets,restful api,uk,united kingdom
Author-Email: "I. Orlovs" <ilja@release.art>, "S. R. Murthy" <s.murthy@tutanota.com>
Maintainer-Email: "I. Orlovs" <ilja@release.art>
License-Expression: MPL-2.0
Classifier: Environment :: Console
Classifier: Programming Language :: Python :: 3
Classifier: Programming Language :: Python :: 3.11
Classifier: Programming Language :: Python :: 3.12
Classifier: Programming Language :: Python :: 3.13
Classifier: Development Status :: 4 - Beta
Classifier: Operating System :: POSIX :: Linux
Classifier: Operating System :: MacOS
Classifier: Operating System :: Microsoft :: Windows
Project-URL: Homepage, https://docs.release.art/fca-api/
Project-URL: Documentation, https://docs.release.art/fca-api/
Project-URL: Repository, https://github.com/release-art/fca-api/
Requires-Python: >=3.11
Requires-Dist: httpx>=0.28.1
Requires-Dist: pydantic>=2.12.5
Provides-Extra: user
